Metadata-Version: 2.1
Name: django-cloudinary-storage
Version: 0.3.0
Summary: Django package that provides Cloudinary storages for both media and static files as well as management commands for removing unnecessary files.
Home-page: https://github.com/klis87/django-cloudinary-storage
Author: Konrad Lisiczynski
Author-email: klisiczynski@gmail.com
License: MIT
Keywords: django cloudinary storage
Platform: UNKNOWN
Classifier: Environment :: Web Environment
Classifier: Framework :: Django
Classifier: Intended Audience :: Developers
Classifier: Operating System :: OS Independent
Classifier: Programming Language :: Python
Classifier: Programming Language :: Python :: 3
Classifier: Programming Language :: Python :: 3.5
Classifier: Programming Language :: Python :: 3.6
Classifier: Programming Language :: Python :: 3.7
Classifier: Programming Language :: Python :: 3.8
Classifier: Topic :: Internet :: WWW/HTTP
Provides-Extra: video
